{
  "apps": [
    {
      "name": "vii_weidong",
      "cwd": "./",
      "script": "main.js",
      "log_date_format": "YYYY-MM-DD HH:mm Z",
      "error_file": "log/erroe.log",
      "out_file": "log/vii_weidong.log",
      "pid_file": "pids/vii_weidong.pid",
      "instances": 1,
      "min_uptime": "200s",
      "max_restarts":200,
      "watch": false,
      "merge_logs": true,
      "exec_interpreter": "node",
      "exec_mode": "cluster",
      "autorestart": true,
      "vizion": false
    }
  ]
}